<?xml version='1.0' encoding='utf-8'?>
<mes:Structure xmlns:xsi="http://www.w3.org/2001/XMLSchema-instance" xmlns:com="http://www.sdmx.org/resources/sdmxml/schemas/v2_1/common" xmlns:md="http://www.sdmx.org/resources/sdmxml/schemas/v2_1/metadata/generic" xmlns:md_ss="http://www.sdmx.org/resources/sdmxml/schemas/v2_1/metadata/structurespecific" xmlns:data="http://www.sdmx.org/resources/sdmxml/schemas/v2_1/data/structurespecific" xmlns:str="http://www.sdmx.org/resources/sdmxml/schemas/v2_1/structure" xmlns:mes="http://www.sdmx.org/resources/sdmxml/schemas/v2_1/message" xmlns:gen="http://www.sdmx.org/resources/sdmxml/schemas/v2_1/data/generic" xmlns:footer="http://www.sdmx.org/resources/sdmxml/schemas/v2_1/message/footer">
  <mes:Header>
    <mes:ID>none</mes:ID>
    <mes:Test>false</mes:Test>
    <mes:Prepared>2025-05-05T00:04:26.693956</mes:Prepared>
    <mes:Sender id="none"/>
    <mes:Source xml:lang="en">Generated by message_ix_models 2025.1.11.dev398+gdaf97af4a.d20250504</mes:Source>
  </mes:Header>
  <mes:Structures>
    <str:Codelists>
      <str:Codelist isExternalReference="false" isFinal="false" agencyID="IIASA_ECE" version="1.0.0" id="CL_TRANSPORT_SCENARIO" urn="urn:sdmx:org.sdmx.infomodel.codelist.Codelist=IIASA_ECE:CL_TRANSPORT_SCENARIO(1.0.0)">
        <str:Code id="SSP1">
          <com:Annotations>
            <com:Annotation id="SSP-URN">
              <com:AnnotationText xml:lang="en">'urn:sdmx:org.sdmx.infomodel.codelist.Code=ICONICS:SSP(2024).1'</com:AnnotationText>
            </com:Annotation>
            <com:Annotation id="is-LED-scenario">
              <com:AnnotationText xml:lang="en">False</com:AnnotationText>
            </com:Annotation>
            <com:Annotation id="EDITS-activity-id">
              <com:AnnotationText xml:lang="en">None</com:AnnotationText>
            </com:Annotation>
            <com:Annotation id="base-scenario-URL">
              <com:AnnotationText xml:lang="en">'ixmp://ixmp-dev/SSP_SSP1_v5.0/baseline_DEFAULT_step_13'</com:AnnotationText>
            </com:Annotation>
          </com:Annotations>
        </str:Code>
        <str:Code id="SSP2">
          <com:Annotations>
            <com:Annotation id="SSP-URN">
              <com:AnnotationText xml:lang="en">'urn:sdmx:org.sdmx.infomodel.codelist.Code=ICONICS:SSP(2024).2'</com:AnnotationText>
            </com:Annotation>
            <com:Annotation id="is-LED-scenario">
              <com:AnnotationText xml:lang="en">False</com:AnnotationText>
            </com:Annotation>
            <com:Annotation id="EDITS-activity-id">
              <com:AnnotationText xml:lang="en">None</com:AnnotationText>
            </com:Annotation>
            <com:Annotation id="base-scenario-URL">
              <com:AnnotationText xml:lang="en">'ixmp://ixmp-dev/SSP_SSP2_v5.0/baseline_DEFAULT_step_13'</com:AnnotationText>
            </com:Annotation>
          </com:Annotations>
        </str:Code>
        <str:Code id="SSP3">
          <com:Annotations>
            <com:Annotation id="SSP-URN">
              <com:AnnotationText xml:lang="en">'urn:sdmx:org.sdmx.infomodel.codelist.Code=ICONICS:SSP(2024).3'</com:AnnotationText>
            </com:Annotation>
            <com:Annotation id="is-LED-scenario">
              <com:AnnotationText xml:lang="en">False</com:AnnotationText>
            </com:Annotation>
            <com:Annotation id="EDITS-activity-id">
              <com:AnnotationText xml:lang="en">None</com:AnnotationText>
            </com:Annotation>
            <com:Annotation id="base-scenario-URL">
              <com:AnnotationText xml:lang="en">'ixmp://ixmp-dev/SSP_SSP3_v5.0/baseline_DEFAULT_step_13'</com:AnnotationText>
            </com:Annotation>
          </com:Annotations>
        </str:Code>
        <str:Code id="SSP4">
          <com:Annotations>
            <com:Annotation id="SSP-URN">
              <com:AnnotationText xml:lang="en">'urn:sdmx:org.sdmx.infomodel.codelist.Code=ICONICS:SSP(2024).4'</com:AnnotationText>
            </com:Annotation>
            <com:Annotation id="is-LED-scenario">
              <com:AnnotationText xml:lang="en">False</com:AnnotationText>
            </com:Annotation>
            <com:Annotation id="EDITS-activity-id">
              <com:AnnotationText xml:lang="en">None</com:AnnotationText>
            </com:Annotation>
            <com:Annotation id="base-scenario-URL">
              <com:AnnotationText xml:lang="en">'ixmp://ixmp-dev/SSP_SSP4_v5.0/baseline_DEFAULT_step_13'</com:AnnotationText>
            </com:Annotation>
          </com:Annotations>
        </str:Code>
        <str:Code id="SSP5">
          <com:Annotations>
            <com:Annotation id="SSP-URN">
              <com:AnnotationText xml:lang="en">'urn:sdmx:org.sdmx.infomodel.codelist.Code=ICONICS:SSP(2024).5'</com:AnnotationText>
            </com:Annotation>
            <com:Annotation id="is-LED-scenario">
              <com:AnnotationText xml:lang="en">False</com:AnnotationText>
            </com:Annotation>
            <com:Annotation id="EDITS-activity-id">
              <com:AnnotationText xml:lang="en">None</com:AnnotationText>
            </com:Annotation>
            <com:Annotation id="base-scenario-URL">
              <com:AnnotationText xml:lang="en">'ixmp://ixmp-dev/SSP_SSP5_v5.0/baseline_DEFAULT_step_13'</com:AnnotationText>
            </com:Annotation>
          </com:Annotations>
        </str:Code>
        <str:Code id="LED-SSP1">
          <com:Annotations>
            <com:Annotation id="SSP-URN">
              <com:AnnotationText xml:lang="en">'urn:sdmx:org.sdmx.infomodel.codelist.Code=ICONICS:SSP(2024).1'</com:AnnotationText>
            </com:Annotation>
            <com:Annotation id="is-LED-scenario">
              <com:AnnotationText xml:lang="en">True</com:AnnotationText>
            </com:Annotation>
            <com:Annotation id="EDITS-activity-id">
              <com:AnnotationText xml:lang="en">None</com:AnnotationText>
            </com:Annotation>
            <com:Annotation id="base-scenario-URL">
              <com:AnnotationText xml:lang="en">'ixmp://ixmp-dev/SSP_SSP1_v5.0/baseline_DEFAULT_step_13'</com:AnnotationText>
            </com:Annotation>
          </com:Annotations>
          <com:Name xml:lang="en">Low Energy Demand/High-with-Low scenario with SSP1 demographics</com:Name>
        </str:Code>
        <str:Code id="LED-SSP2">
          <com:Annotations>
            <com:Annotation id="SSP-URN">
              <com:AnnotationText xml:lang="en">'urn:sdmx:org.sdmx.infomodel.codelist.Code=ICONICS:SSP(2024).2'</com:AnnotationText>
            </com:Annotation>
            <com:Annotation id="is-LED-scenario">
              <com:AnnotationText xml:lang="en">True</com:AnnotationText>
            </com:Annotation>
            <com:Annotation id="EDITS-activity-id">
              <com:AnnotationText xml:lang="en">None</com:AnnotationText>
            </com:Annotation>
            <com:Annotation id="base-scenario-URL">
              <com:AnnotationText xml:lang="en">'ixmp://ixmp-dev/SSP_SSP2_v5.0/baseline_DEFAULT_step_13'</com:AnnotationText>
            </com:Annotation>
          </com:Annotations>
          <com:Name xml:lang="en">Low Energy Demand/High-with-Low scenario with SSP2 demographics</com:Name>
        </str:Code>
        <str:Code id="EDITS-CA">
          <com:Annotations>
            <com:Annotation id="SSP-URN">
              <com:AnnotationText xml:lang="en">'urn:sdmx:org.sdmx.infomodel.codelist.Code=ICONICS:SSP(2024).2'</com:AnnotationText>
            </com:Annotation>
            <com:Annotation id="is-LED-scenario">
              <com:AnnotationText xml:lang="en">False</com:AnnotationText>
            </com:Annotation>
            <com:Annotation id="EDITS-activity-id">
              <com:AnnotationText xml:lang="en">'CA'</com:AnnotationText>
            </com:Annotation>
            <com:Annotation id="base-scenario-URL">
              <com:AnnotationText xml:lang="en">'ixmp://ixmp-dev/SSP_SSP2_v5.0/baseline_DEFAULT_step_13'</com:AnnotationText>
            </com:Annotation>
          </com:Annotations>
          <com:Name xml:lang="en">EDITS scenario with ITF PASTA 'CA' activity</com:Name>
        </str:Code>
        <str:Code id="EDITS-HA">
          <com:Annotations>
            <com:Annotation id="SSP-URN">
              <com:AnnotationText xml:lang="en">'urn:sdmx:org.sdmx.infomodel.codelist.Code=ICONICS:SSP(2024).2'</com:AnnotationText>
            </com:Annotation>
            <com:Annotation id="is-LED-scenario">
              <com:AnnotationText xml:lang="en">False</com:AnnotationText>
            </com:Annotation>
            <com:Annotation id="EDITS-activity-id">
              <com:AnnotationText xml:lang="en">'HA'</com:AnnotationText>
            </com:Annotation>
            <com:Annotation id="base-scenario-URL">
              <com:AnnotationText xml:lang="en">'ixmp://ixmp-dev/SSP_SSP2_v5.0/baseline_DEFAULT_step_13'</com:AnnotationText>
            </com:Annotation>
          </com:Annotations>
          <com:Name xml:lang="en">EDITS scenario with ITF PASTA 'HA' activity</com:Name>
        </str:Code>
      </str:Codelist>
    </str:Codelists>
  </mes:Structures>
</mes:Structure>
